jsonpatch.py
jsonpatch-1.30.data/scripts/jsondiff
jsonpatch-1.30.data/scripts/jsonpatch
jsonpatch-1.30.dist-info/AUTHORS
jsonpatch-1.30.dist-info/COPYING
jsonpatch-1.30.dist-info/METADATA
jsonpatch-1.30.dist-info/WHEEL
jsonpatch-1.30.dist-info/top_level.txt
jsonpatch-1.30.dist-info/RECORD
