Metadata-Version: 2.1
Name: jsonpatch
Version: 1.30
Summary: Apply JSON-Patches (RFC 6902) 
Home-page: https://github.com/stefankoegl/python-json-patch
Author: Stefan Kögl
Author-email: stefan@skoegl.net
License: Modified BSD License
Project-URL: Website, https://github.com/stefankoegl/python-json-patch
Project-URL: Repository, https://github.com/stefankoegl/python-json-patch.git
Project-URL: Documentation, https://python-json-patch.readthedocs.org/
Project-URL: PyPI, https://pypi.org/pypi/jsonpatch
Project-URL: Tests, https://travis-ci.org/stefankoegl/python-json-patch
Project-URL: Test Coverage, https://coveralls.io/r/stefankoegl/python-json-patch
Platform: UNKNOWN
Classifier: Development Status :: 5 - Production/Stable
Classifier: Environment :: Console
Classifier: Intended Audience :: Developers
Classifier: License :: OSI Approved :: BSD License
Classifier: Operating System :: OS Independent
Classifier: Programming Language :: Python
Classifier: Programming Language :: Python :: 2
Classifier: Programming Language :: Python :: 2.7
Classifier: Programming Language :: Python :: 3
Classifier: Programming Language :: Python :: 3.5
Classifier: Programming Language :: Python :: 3.6
Classifier: Programming Language :: Python :: 3.7
Classifier: Programming Language :: Python :: 3.8
Classifier: Programming Language :: Python :: 3.9
Classifier: Programming Language :: Python :: Implementation :: CPython
Classifier: Programming Language :: Python :: Implementation :: PyPy
Classifier: Topic :: Software Development :: Libraries
Classifier: Topic :: Utilities
Requires-Python: >=2.7, !=3.0.*, !=3.1.*, !=3.2.*, !=3.3.*, !=3.4.*
Requires-Dist: jsonpointer (>=1.9)
